mvm/DOELib.py
mvm/__init__.py
mvm/designMarginsLib.py
mvm/fuzzyLib.py
mvm/uncertaintyLib.py
mvm/utilities.py
mvmlib-0.5.10.dist-info/WHEEL
mvmlib-0.5.10.dist-info/METADATA
mvmlib-0.5.10.dist-info/RECORD
