Metadata-Version: 2.1
Name: mvmlib
Version: 0.5.10
Summary: Margin Value Method Library
Author-email: Khalil Al Handawi <khalil.alhandawi@mail.mcgill.ca>
Requires-Python: >=3.8
Requires-Dist: matplotlib<=3.8.4
Requires-Dist: pyDOE2<=1.3.0
Requires-Dist: scikit-fuzzy<=0.4.2
Requires-Dist: smt<=1.3.0
Requires-Dist: multiprocess<=0.70.16
Requires-Dist: sphinx ; extra == "doc"
Requires-Dist: sphinx-autobuild ; extra == "doc"
Requires-Dist: sphinx-rtd-theme ; extra == "doc"
Requires-Dist: nbsphinx ; extra == "doc"
Requires-Dist: sphinx-copybutton ; extra == "doc"
Requires-Dist: pytest>=6.2.5 ; extra == "test"
Requires-Dist: pytest-cov==3.0.0 ; extra == "test"
Requires-Dist: pytest-dependency==0.5.1 ; extra == "test"
Requires-Dist: pandoc ; extra == "test"
Project-URL: Source, https://github.com/sed-group/mvmlib
Provides-Extra: doc
Provides-Extra: test
